koinapy/__init__.py
koinapy/__main__.py
koinapy/grpc.py
koinapy-0.0.10.dist-info/METADATA
koinapy-0.0.10.dist-info/WHEEL
koinapy-0.0.10.dist-info/RECORD
